reixs/LoadData.py
reixs/ReadData.py
reixs/__init__.py
reixs/add_subtract.py
reixs/beamline_info.py
reixs/edges.py
reixs/mca.py
reixs/mesh.py
reixs/parser.py
reixs/rixs_readutil.py
reixs/rsxs_mcp.py
reixs/rsxs_readutil.py
reixs/sca.py
reixs/simplemath.py
reixs/spec_config.py
reixs/util.py
reixs/xeol.py
reixs-0.6.8.dist-info/LICENSE
reixs-0.6.8.dist-info/METADATA
reixs-0.6.8.dist-info/WHEEL
reixs-0.6.8.dist-info/top_level.txt
reixs-0.6.8.dist-info/RECORD
