Metadata-Version: 2.1
Name: reixs
Version: 0.6.8
Summary: Library to analyse, plot, and export data taken at the REIXS Beamline at the Canadian Light Source, Saskatoon, Canada.
Home-page: https://github.com/pmb399/REIXSAnalysis
Author: Patrick Braun
Author-email: patrick.braun@usask.ca
Project-URL: Bug Tracker, https://github.com/pmb399/REIXSAnalysis
Project-URL: Beamline Information, https://reixs.lightsource.ca
Classifier: Programming Language :: Python :: 3
Classifier: License :: OSI Approved :: MIT License
Classifier: Operating System :: OS Independent
Requires-Python: >=3.6
License-File: LICENSE
Requires-Dist: numpy >=1.26.1
Requires-Dist: pandas >1.5.0
Requires-Dist: bokeh <3,>=2.3.3
Requires-Dist: scipy >=1.11.3
Requires-Dist: ipywidgets
Requires-Dist: ipyfilechooser ==0.6.0
Requires-Dist: h5py >=3.10.0
Requires-Dist: shapely >=2.0.2
